ZJS_Package/Log_Configuration_FCN.py
ZJS_Package/__init__.py
zjs_package-1.0.0.dist-info/licenses/LICENSE
zjs_package-1.0.0.dist-info/METADATA
zjs_package-1.0.0.dist-info/WHEEL
zjs_package-1.0.0.dist-info/top_level.txt
zjs_package-1.0.0.dist-info/RECORD
